{
  "routes": [
    {
      "method": "GET",
      "path": "/sizes",
      "handler": "size.find",
      "config": {
        "policies": []
      }
    },
    {
      "method": "GET",
      "path": "/sizes/count",
      "handler": "size.count",
      "config": {
        "policies": []
      }
    },
    {
      "method": "GET",
      "path": "/sizes/:id",
      "handler": "size.findOne",
      "config": {
        "policies": []
      }
    },
    {
      "method": "POST",
      "path": "/sizes",
      "handler": "size.create",
      "config": {
        "policies": []
      }
    },
    {
      "method": "PUT",
      "path": "/sizes/:id",
      "handler": "size.update",
      "config": {
        "policies": []
      }
    },
    {
      "method": "DELETE",
      "path": "/sizes/:id",
      "handler": "size.delete",
      "config": {
        "policies": []
      }
    }
  ]
}
